Metadata-Version: 2.1
Name: crlib
Version: 1.2.1
Summary: Cuboid Raptor's Lib Rary, A Garbage Collection Of Garbage For Your Garbage Needs™
Home-page: https://github.com/CuboidRaptor/crlib
Author: Cuboid Raptor
Author-email: fanjas112358@gmail.com
License: GNU GPLv3
Requires-Python: >=3.6
License-File: LICENSE
